{
  "project_info": {
    "project_number": "378377079872",
    "project_id": "sberinvest-cb0ba",
    "storage_bucket": "sberinvest-cb0ba.firebasestorage.app"
  },
  "client": [
    {
      "client_info": {
        "mobilesdk_app_id": "1:378377079872:android:aa6fbbd0759d1a597a63a5",
        "android_client_info": {
          "package_name": "com.sbe.rand.inve.st"
        }
      },
      "oauth_client": [],
      "api_key": [
        {
          "current_key": "AIzaSyDAD8BcMML2HrHZdf2Iw67H4gighgpg5hs"
        }
      ],
      "services": {
        "appinvite_service": {
          "other_platform_oauth_client": []
        }
      }
    }
  ],
  "configuration_version": "1"
}